{
  "id": "list-posts_f8a2b1c0",
  "apiType": "rest",
  "name": "List Posts",
  "description": "Fetch all posts from JSONPlaceholder",
  "httpRequestModel": {
    "method": "get",
    "url": "{{base_url}}/posts/1",
    "headers": [
      {
        "name": "User-Agent",
        "value": "{{user_agent}}"
      },
      {
        "name": "Accept",
        "value": "application/json"
      }
    ],
    "params": null,
    "authModel": {
      "type": "none",
      "apikey": null,
      "bearer": null,
      "basic": null,
      "jwt": null,
      "digest": null,
      "oauth1": null,
      "oauth2": null
    },
    "isHeaderEnabledList": [
      true,
      true
    ],
    "isParamEnabledList": null,
    "bodyContentType": "json",
    "body": null,
    "query": null,
    "formData": null
  },
  "responseStatus": -1,
  "message": "FormatException: %7B%7Bbase_url%7D%7D is not a valid link-local address but contains %. Scope id should be used as part of link-local address. (at character 1)\n%7B%7Bbase_url%7D%7D\n^\n",
  "preRequestScript": null,
  "postRequestScript": null,
  "aiRequestModel": null
}